{
  "packageName": "FactSet.SDK.FactSetProgrammaticEnvironment",
  "packageVersion": "0.21.8",
  "packageGuid": "{042dcae3-8d9a-5280-8b35-54172acd9c98}",
  "packageUrl": "https://github.com/FactSet/enterprise-sdk/tree/main/code/dotnet/FactSetProgrammaticEnvironment/v1",
  "targetFramework": "netstandard2.0",
  "caseInsensitiveResponseHeaders": true,
  "packageAuthors": "FactSet Research Systems",
  "packageTitle": "FactSet SDK",
  "packageDescription": "FactSet Programmatic Environment client library for .NET",
  "packageCompany": "FactSet Research Systems",
  "packageProductName": "FactSet SDK - FactSet Programmatic Environment",
  "packageCopyright": "",
  "gitHost": "github.com",
  "gitUserId": "factset",
  "gitRepoId": "enterprise-sdk",
  "licenseId": "Apache-2.0",
  "licenseUrl": "https://www.apache.org/licenses/LICENSE-2.0",
  "releaseNote": "Refer to Changelog on GitHub source repository",
  "packageTags": "FactSet;API;SDK",
  "httpUserAgent": "fds-sdk/dotnet/FactSetProgrammaticEnvironment/0.21.8",
  "files": {
    "LICENSE": {}
  },
  "useOneOfDiscriminatorLookup": true
}
