{
  "packageName": "FactSet.SDK.FactSetTrading",
  "packageVersion": "0.22.3",
  "packageGuid": "{bda92720-460a-5e1b-8abf-aaf43bb055ab}",
  "packageUrl": "https://github.com/FactSet/enterprise-sdk/tree/main/code/dotnet/FactSetTrading/v1",
  "targetFramework": "netstandard2.0",
  "caseInsensitiveResponseHeaders": true,
  "packageAuthors": "FactSet Research Systems",
  "packageTitle": "FactSet SDK",
  "packageDescription": "FactSet Trading client library for .NET",
  "packageCompany": "FactSet Research Systems",
  "packageProductName": "FactSet SDK - FactSet Trading",
  "packageCopyright": "",
  "gitHost": "github.com",
  "gitUserId": "factset",
  "gitRepoId": "enterprise-sdk",
  "licenseId": "Apache-2.0",
  "licenseUrl": "https://www.apache.org/licenses/LICENSE-2.0",
  "releaseNote": "Refer to Changelog on GitHub source repository",
  "packageTags": "FactSet;API;SDK",
  "httpUserAgent": "fds-sdk/dotnet/FactSetTrading/0.22.3",
  "files": {
    "LICENSE": {}
  },
  "useOneOfDiscriminatorLookup": true
}
